{
  "routes": {
    "/": {},
    "/about-us": {},
    "/contact": {},
    "/home": {},
    "/login": {},
    "/movies": {},
    "/movies/1022787": {},
    "/movies/1061474": {},
    "/movies/1078605": {},
    "/movies/1083433": {},
    "/movies/1087192": {},
    "/movies/1151334": {},
    "/movies/1175942": {},
    "/movies/1234821": {},
    "/movies/1241470": {},
    "/movies/1242011": {},
    "/movies/1300116": {},
    "/movies/1311031": {},
    "/movies/13494": {},
    "/movies/1382406": {},
    "/movies/1389158": {},
    "/movies/1429739": {},
    "/movies/575265": {},
    "/movies/755898": {},
    "/movies/803796": {},
    "/movies/911430": {}
  }
}